cfripper/__init__.py
cfripper/__main__.py
cfripper/boto3_client.py
cfripper/cli.py
cfripper/cloudformation_actions_only_accepts_wildcard.py
cfripper/exceptions.py
cfripper/rule_processor.py
cfripper/config/__init__.py
cfripper/config/config.py
cfripper/config/constants.py
cfripper/config/filter.py
cfripper/config/logger.py
cfripper/config/regex.py
cfripper/config/rule_config.py
cfripper/config/pluggy/__init__.py
cfripper/config/pluggy/hookspec.py
cfripper/config/pluggy/utils.py
cfripper/config/rule_configs/__init__.py
cfripper/config/rule_configs/allow_http_ports_open_to_world.py
cfripper/config/rule_configs/example_rules_config_for_cli.py
cfripper/config/rule_configs/firehose_ips.py
cfripper/model/__init__.py
cfripper/model/enums.py
cfripper/model/result.py
cfripper/model/utils.py
cfripper/rules/__init__.py
cfripper/rules/base_rules.py
cfripper/rules/cloudformation_authentication.py
cfripper/rules/cross_account_trust.py
cfripper/rules/ebs_volume_has_sse.py
cfripper/rules/ec2_security_group.py
cfripper/rules/hardcoded_RDS_password.py
cfripper/rules/iam_roles.py
cfripper/rules/kms_key_rotation_enabled.py
cfripper/rules/kms_key_wildcard_principal.py
cfripper/rules/managed_policy_on_user.py
cfripper/rules/policy_on_user.py
cfripper/rules/privilege_escalation.py
cfripper/rules/public_elb_checker_rule.py
cfripper/rules/rds_security_group.py
cfripper/rules/s3_bucket_policy.py
cfripper/rules/s3_lifecycle_configuration.py
cfripper/rules/s3_object_versioning.py
cfripper/rules/s3_public_access.py
cfripper/rules/sns_topic_policy.py
cfripper/rules/sqs_queue_policy.py
cfripper/rules/stack_name_matches_regex.py
cfripper/rules/storage_encrypted_rule.py
cfripper/rules/wildcard_policies.py
cfripper/rules/wildcard_principals.py
cfripper/rules/wildcard_resource_rule.py
cfripper-1.19.1.dist-info/licenses/LICENSE.md
cfripper-1.19.1.dist-info/METADATA
cfripper-1.19.1.dist-info/WHEEL
cfripper-1.19.1.dist-info/entry_points.txt
cfripper-1.19.1.dist-info/top_level.txt
cfripper-1.19.1.dist-info/RECORD
