Metadata-Version: 2.4
Name: cfripper
Version: 1.19.1
Summary: Library and CLI tool for analysing CloudFormation templates and check them for security compliance.
Author-email: Skyscanner Security <security@skyscanner.net>
License:                                  Apache License
Project-URL: documentation, https://cfripper.readthedocs.io/
Project-URL: repository, https://github.com/Skyscanner/cfripper
Keywords: security,cloudformation,aws,cli
Classifier: Development Status :: 5 - Production/Stable
Classifier: Environment :: Console
Classifier: Intended Audience :: Developers
Classifier: License :: OSI Approved :: Apache Software License
Classifier: Operating System :: OS Independent
Classifier: Programming Language :: Python :: 3
Classifier: Programming Language :: Python :: 3.10
Classifier: Programming Language :: Python :: 3.11
Classifier: Programming Language :: Python :: 3.12
Classifier: Programming Language :: Python :: 3.13
Classifier: Programming Language :: Python :: 3.14
Classifier: Topic :: Security
Requires-Python: >=3.10.0
License-File: LICENSE.md
Requires-Dist: boto3<2,>=1.4.7
Requires-Dist: cfn_flip>=1.2.0
Requires-Dist: click>=8.0.0
Requires-Dist: pluggy>=0.13.1
Requires-Dist: pycfmodel>=1.2.0
Requires-Dist: pydash>=4.7.6
Requires-Dist: PyYAML>=4.2b1
Provides-Extra: dev
Requires-Dist: moto[all]>=5; extra == "dev"
Requires-Dist: pytest-cov>=2.5.1; extra == "dev"
Requires-Dist: pytest>=3.6; extra == "dev"
Requires-Dist: ruff>=0.7.0; extra == "dev"
Requires-Dist: uv>=0.8.0; extra == "dev"
Provides-Extra: docs
Requires-Dist: mkdocs==1.6.1; extra == "docs"
Requires-Dist: mkdocs-macros-plugin==1.4.0; extra == "docs"
Requires-Dist: mkdocs-material==8.2.8; extra == "docs"
Requires-Dist: mkdocs-material-extensions==1.0.3; extra == "docs"
Requires-Dist: mkdocs-minify-plugin==0.8.0; extra == "docs"
Dynamic: license-file
